[
    {
        "id": 1002901001,
        "pid": "/",
        "type": 2,
        "subtype": 0,
        "name": "Support",
        "uri": null,
        "target": "self",
        "icon": "fa fa-question-circle",
        "order": 80,
        "from": "Support",
        "permission": { "permission": 2, "type": null, "element": null },
        "parent": 0,
        "children": [
            {
                "id": 1002901101,
                "pid": "/",
                "type": 2,
                "subtype": 1,
                "name": "Ticket",
                "uri": "{/prefix}support/list?{?}",
                "target": "self",
                "icon": null,
                "order": 1,
                "from": "Support",
                "permission": { "permission": 2, "type": null, "element": null },
                "parent": 1002901001,
                "children": [
                    {
                        "id": 1002903101,
                        "pid": "/support",
                        "type": 3,
                        "subtype": 1,
                        "name": "List",
                        "uri": "{/prefix}support/list?{?}",
                        "target": "self",
                        "icon": null,
                        "order": 1,
                        "from": "Support",
                        "permission": { "permission": 2, "type": null, "element": null },
                        "parent": 1002901101,
                        "children": [
                        ]
                    },
                    {
                        "id": 1002903201,
                        "pid": "/support",
                        "type": 3,
                        "subtype": 1,
                        "name": "Create",
                        "uri": "{/prefix}support/create?{?}",
                        "target": "self",
                        "icon": null,
                        "order": 5,
                        "from": "Support",
                        "permission": { "permission": 4, "type": null, "element": null },
                        "parent": 1002901101,
                        "children": [
                        ]
                    }
                ]
            },
            {
                "id": 1002901201,
                "pid": "/",
                "type": 2,
                "subtype": 1,
                "name": "Settings",
                "uri": "{/prefix}support/settings/dashboard?{?}",
                "target": "self",
                "icon": null,
                "order": 5,
                "from": "Support",
                "permission": { "permission": 2, "type": null, "element": null },
                "parent": 1002901001,
                "children": [
                ]
            },
            {
                "id": 1002901301,
                "pid": "/",
                "type": 2,
                "subtype": 1,
                "name": "Analysis",
                "uri": "{/prefix}support/analysis/dashboard?{?}",
                "target": "self",
                "icon": null,
                "order": 10,
                "from": "Support",
                "permission": { "permission": 2, "type": null, "element": null },
                "parent": 1002901001,
                "children": [
                ]
            }
        ]
    },
    {
        "id": 1002902001,
        "pid": "/",
        "type": 2,
        "subtype": 1,
        "name": "Support",
        "uri": "{/prefix}private/support/dashboard?{?}",
        "target": "self",
        "icon": null,
        "order": 5,
        "from": "Support",
        "permission": { "permission": 2, "type": null, "element": null },
        "parent": 1003401001,
        "children": [
        ]
    }
]
